ofjustpy_plugins/EmacsStyle.py
ofjustpy_plugins/PyCodeFormatter.py
ofjustpy_plugins/__init__.py
ofjustpy_plugins-0.0.1.dist-info/LICENSE
ofjustpy_plugins-0.0.1.dist-info/WHEEL
ofjustpy_plugins-0.0.1.dist-info/METADATA
ofjustpy_plugins-0.0.1.dist-info/RECORD
